image_viewer/wsgi.py
image_viewer/__init__.py
image_viewer/urls.py
image_viewer/settings.py
image_scroller-0.1.dist-info/WHEEL
image_scroller-0.1.dist-info/METADATA
image_scroller-0.1.dist-info/RECORD
image_scroller-0.1.dist-info/top_level.txt
image_scroller-0.1.dist-info/metadata.json
image_scroller-0.1.dist-info/DESCRIPTION.rst
