Metadata-Version: 2.0
Name: image-scroller
Version: 0.1
Summary: A simple image viewer with vertical scroller.
Home-page: UNKNOWN
Author: Mayur Swami
Author-email: UNKNOWN
License: UNKNOWN
Platform: UNKNOWN
